{"chunk_definitions":[{"row":8,"row_count":1,"visible":true,"expansion_state":0,"options":{"engine":"r","label":"setup","include":false,"dev":"png"},"document_id":"49793129","chunk_id":"csetup_chunk","chunk_label":"setup"},{"row":17,"row_count":1,"visible":true,"expansion_state":0,"options":{"engine":"r","label":"unnamed-chunk-50","dev":"png"},"document_id":"49793129","chunk_id":"c6jem06j2ncmf","chunk_label":"unnamed-chunk-1"},{"row":25,"row_count":1,"visible":true,"expansion_state":0,"options":{"engine":"r","label":"unnamed-chunk-51","dev":"png"},"document_id":"49793129","chunk_id":"ce7iay4nvxedf","chunk_label":"unnamed-chunk-2"},{"row":30,"row_count":1,"visible":true,"expansion_state":0,"options":{"engine":"r","label":"unnamed-chunk-52","dev":"png"},"document_id":"49793129","chunk_id":"c65a880d56ow1","chunk_label":"unnamed-chunk-3"},{"row":36,"row_count":1,"visible":true,"expansion_state":0,"options":{"engine":"r","label":"unnamed-chunk-53","dev":"png"},"document_id":"49793129","chunk_id":"c4757tjos53ax","chunk_label":"unnamed-chunk-4"},{"row":60,"row_count":1,"visible":true,"expansion_state":0,"options":{"engine":"r","label":"unnamed-chunk-54","dev":"png"},"document_id":"49793129","chunk_id":"cmhuamlbqe0vw","chunk_label":"unnamed-chunk-5"},{"row":70,"row_count":1,"visible":true,"expansion_state":0,"options":{"engine":"r","label":"unnamed-chunk-55","dev":"png"},"document_id":"49793129","chunk_id":"ch49ko0bjhsf4","chunk_label":"unnamed-chunk-6"},{"row":98,"row_count":1,"visible":true,"expansion_state":0,"options":{"engine":"r","label":"unnamed-chunk-80","dev":"png"},"document_id":"49793129","chunk_id":"cb662ahtmlu9g","chunk_label":"unnamed-chunk-7"},{"row":107,"row_count":1,"visible":true,"expansion_state":0,"options":{"engine":"r","label":"unnamed-chunk-207","dev":"png"},"document_id":"49793129","chunk_id":"c874rpygmlwby","chunk_label":"unnamed-chunk-8"},{"row":135,"row_count":1,"visible":true,"expansion_state":0,"options":{"engine":"r","label":"unnamed-chunk-56","dev":"png"},"document_id":"49793129","chunk_id":"c4k20ti357rra","chunk_label":"unnamed-chunk-9"},{"row":147,"row_count":1,"visible":true,"expansion_state":0,"options":{"engine":"r","label":"unnamed-chunk-57","dev":"png"},"document_id":"49793129","chunk_id":"cj42bwzcirilj","chunk_label":"unnamed-chunk-10"},{"row":156,"row_count":1,"visible":true,"expansion_state":0,"options":{"engine":"r","label":"unnamed-chunk-58","dev":"png"},"document_id":"49793129","chunk_id":"c7y2quopodong","chunk_label":"unnamed-chunk-11"},{"row":169,"row_count":1,"visible":true,"expansion_state":0,"options":{"engine":"r","label":"unnamed-chunk-59","dev":"png"},"document_id":"49793129","chunk_id":"cuk9d3f4t19y9","chunk_label":"unnamed-chunk-12"},{"row":199,"row_count":1,"visible":true,"expansion_state":0,"options":{"engine":"r","label":"unnamed-chunk-269","dev":"png"},"document_id":"49793129","chunk_id":"c4a0espqm4kbl","chunk_label":"unnamed-chunk-13"},{"row":205,"row_count":1,"visible":true,"expansion_state":0,"options":{"engine":"r","label":"unnamed-chunk-61","dev":"png"},"document_id":"49793129","chunk_id":"c6fjvfgmx2jji","chunk_label":"unnamed-chunk-14"},{"row":219,"row_count":1,"visible":true,"expansion_state":0,"options":{"engine":"r","label":"unnamed-chunk-65","dev":"png"},"document_id":"49793129","chunk_id":"coeql24f56zt8","chunk_label":"unnamed-chunk-15"},{"row":225,"row_count":1,"visible":true,"expansion_state":0,"options":{"engine":"r","label":"unnamed-chunk-66","dev":"png"},"document_id":"49793129","chunk_id":"cdf2hu3p7ccnv","chunk_label":"unnamed-chunk-16"},{"row":234,"row_count":1,"visible":true,"expansion_state":0,"options":{"engine":"r","label":"unnamed-chunk-71","dev":"png"},"document_id":"49793129","chunk_id":"cza8x9ixnjmla","chunk_label":"unnamed-chunk-17"},{"row":251,"row_count":1,"visible":true,"expansion_state":0,"options":{"engine":"r","label":"unnamed-chunk-75","dev":"png"},"document_id":"49793129","chunk_id":"cf4y1gohn2qio","chunk_label":"unnamed-chunk-18"}],"doc_write_time":1714409566,"working_dir":null,"default_chunk_options":{"echo":false}}